datasette_placekey/__init__.py
datasette_placekey-0.1.dist-info/METADATA
datasette_placekey-0.1.dist-info/WHEEL
datasette_placekey-0.1.dist-info/entry_points.txt
datasette_placekey-0.1.dist-info/top_level.txt
datasette_placekey-0.1.dist-info/RECORD
