Metadata-Version: 2.1
Name: datasette-placekey
Version: 0.1
Summary: SQL functions for working with placekeys
Home-page: https://github.com/simonw/datasette-placekey
Author: Simon Willison
License: Apache License, Version 2.0
Project-URL: Issues, https://github.com/simonw/datasette-placekey/issues
Project-URL: CI, https://github.com/simonw/datasette-placekey/actions
Project-URL: Changelog, https://github.com/simonw/datasette-placekey/releases
Platform: UNKNOWN
Requires-Python: >=3.6
Requires-Dist: datasette
Requires-Dist: placekey
Provides-Extra: test
Requires-Dist: pytest ; extra == 'test'
Requires-Dist: pytest-asyncio ; extra == 'test'
